plone.outputfilters-5.0.5-py3.13-nspkg.pth
plone/outputfilters/README.rst
plone/outputfilters/__init__.py
plone/outputfilters/configure.zcml
plone/outputfilters/interfaces.py
plone/outputfilters/mimetype.py
plone/outputfilters/setuphandlers.py
plone/outputfilters/testing.py
plone/outputfilters/browser/__init__.py
plone/outputfilters/browser/captioned_image.pt
plone/outputfilters/browser/captioned_image.py
plone/outputfilters/browser/configure.zcml
plone/outputfilters/browser/resolveuid.py
plone/outputfilters/filters/__init__.py
plone/outputfilters/filters/configure.zcml
plone/outputfilters/filters/example.py
plone/outputfilters/filters/picture_variants.py
plone/outputfilters/filters/resolveuid_and_caption.py
plone/outputfilters/profiles/default/plone.outputfilters.txt
plone/outputfilters/tests/__init__.py
plone/outputfilters/tests/image.jpg
plone/outputfilters/tests/test_apply_filters.py
plone/outputfilters/tests/test_docs.py
plone/outputfilters/tests/test_picture_variants.py
plone/outputfilters/tests/test_resolveuid_and_caption.py
plone/outputfilters/tests/test_transforms.py
plone/outputfilters/transforms/__init__.py
plone/outputfilters/transforms/html_to_plone_outputfilters_html.py
plone/outputfilters/transforms/plone_outputfilters_html_to_html.py
plone_outputfilters-5.0.5.dist-info/METADATA
plone_outputfilters-5.0.5.dist-info/WHEEL
plone_outputfilters-5.0.5.dist-info/entry_points.txt
plone_outputfilters-5.0.5.dist-info/namespace_packages.txt
plone_outputfilters-5.0.5.dist-info/top_level.txt
plone_outputfilters-5.0.5.dist-info/RECORD
