Metadata-Version: 2.4
Name: plone.outputfilters
Version: 5.0.5
Summary: Transformations applied to HTML in Plone text fields as they are rendered
Home-page: http://github.com/plone/plone.outputfilters
Author: David Glick, Plone Foundation
Author-email: davidglick@groundwire.org
License: GPL
Keywords: plone transform filter uid caption
Classifier: Development Status :: 5 - Production/Stable
Classifier: Framework :: Plone
Classifier: Framework :: Plone :: 6.0
Classifier: Framework :: Plone :: Core
Classifier: License :: OSI Approved :: GNU General Public License (GPL)
Classifier: Programming Language :: Python
Classifier: Programming Language :: Python :: 3.8
Classifier: Programming Language :: Python :: 3.9
Classifier: Programming Language :: Python :: 3.10
Classifier: Programming Language :: Python :: 3.11
Requires-Python: >=3.8
Requires-Dist: setuptools
Requires-Dist: beautifulsoup4
Requires-Dist: Products.GenericSetup
Requires-Dist: Products.MimetypesRegistry
Requires-Dist: Products.PortalTransforms>=2.0
Requires-Dist: plone.app.uuid>=2.2.0
Requires-Dist: plone.base
Requires-Dist: plone.namedfile
Requires-Dist: plone.registry
Requires-Dist: plone.uuid
Requires-Dist: Zope
Requires-Dist: zope.cachedescriptors
Provides-Extra: test
Requires-Dist: plone.app.contenttypes[test]; extra == "test"
Requires-Dist: plone.app.testing; extra == "test"
Requires-Dist: plone.app.textfield; extra == "test"
Requires-Dist: plone.namedfile; extra == "test"
Requires-Dist: plone.testing; extra == "test"
Dynamic: author
Dynamic: author-email
Dynamic: classifier
Dynamic: description
Dynamic: home-page
Dynamic: keywords
Dynamic: license
Dynamic: provides-extra
Dynamic: requires-dist
Dynamic: requires-python
Dynamic: summary
